py_solc-3.1.0.dist-info/DESCRIPTION.rst
py_solc-3.1.0.dist-info/METADATA
py_solc-3.1.0.dist-info/RECORD
py_solc-3.1.0.dist-info/WHEEL
py_solc-3.1.0.dist-info/metadata.json
py_solc-3.1.0.dist-info/top_level.txt
solc/__init__.py
solc/exceptions.py
solc/install.py
solc/main.py
solc/wrapper.py
solc/utils/__init__.py
solc/utils/filesystem.py
solc/utils/string.py
solc/utils/types.py
