Metadata-Version: 1.2
Name: py-solc
Version: 3.1.0
Summary: Python wrapper around the solc binary
Home-page: https://github.com/ethereum/py-solc
Author: Piper Merriam
Author-email: pipermerriam@gmail.com
License: MIT
Keywords: ethereum solidity solc
Platform: UNKNOWN
Classifier: Intended Audience :: Developers
Classifier: License :: OSI Approved :: MIT License
Classifier: Natural Language :: English
Classifier: Programming Language :: Python :: 2
Classifier: Programming Language :: Python :: 2.7
Classifier: Programming Language :: Python :: 3
Classifier: Programming Language :: Python :: 3.4
Classifier: Programming Language :: Python :: 3.5
Requires-Python: >=3.4, <4
